revisit_bpr/__init__.py
revisit_bpr/datasets/__init__.py
revisit_bpr/datasets/jsonl.py
revisit_bpr/metrics/__init__.py
revisit_bpr/metrics/auc.py
revisit_bpr/metrics/fbeta.py
revisit_bpr/metrics/map.py
revisit_bpr/metrics/metric.py
revisit_bpr/metrics/ndcg.py
revisit_bpr/metrics/precision.py
revisit_bpr/metrics/recall.py
revisit_bpr/models/__init__.py
revisit_bpr/models/ae/__init__.py
revisit_bpr/models/ae/kl_scheduler.py
revisit_bpr/models/ae/loss.py
revisit_bpr/models/ae/multdae.py
revisit_bpr/models/ae/multvae.py
revisit_bpr/models/bpr/__init__.py
revisit_bpr/models/bpr/loss.py
revisit_bpr/models/bpr/model.py
revisit_bpr/models/ease/__init__.py
revisit_bpr/models/ease/model.py
revisit_bpr/models/popularity/__init__.py
revisit_bpr/models/popularity/model.py
revisit_bpr/modules/__init__.py
revisit_bpr/modules/activation.py
revisit_bpr/modules/mlp.py
revisit_bpr/modules/neg_samplers.py
revisit_bpr-0.0.1.dist-info/LICENSE
revisit_bpr-0.0.1.dist-info/METADATA
revisit_bpr-0.0.1.dist-info/WHEEL
revisit_bpr-0.0.1.dist-info/RECORD
