Metadata-Version: 2.1
Name: revisit-bpr
Version: 0.0.1
Summary: Repository for the paper: "Revisiting BPR: A Replicability Study of a Common Recommender System Baseline"
Home-page: https://github.com/nemexur/revisit-bpr
Author: Aleksandr Milogradskii
Author-email: alex.milogradsky@gmail.com
Requires-Python: >=3.10,<3.13
Classifier: Programming Language :: Python :: 3
Classifier: Programming Language :: Python :: 3.10
Classifier: Programming Language :: Python :: 3.11
Classifier: Programming Language :: Python :: 3.12
Requires-Dist: accelerate (>=0.28.0,<0.29.0)
Requires-Dist: einops (>=0.6.1,<0.7.0)
Requires-Dist: numpy (>=1.25.2,<2.0.0)
Requires-Dist: safetensors (>=0.4.2,<0.5.0)
Requires-Dist: scikit-learn (>=1.3.0,<2.0.0)
Requires-Dist: torch (>=2.2.1,<3.0.0)
Project-URL: Repository, https://github.com/nemexur/revisit-bpr
